pyjrk/__init__.py
pyjrk/drivers/linux/libpololu-jrk2-1.so
pyjrk/drivers/linux/libusbp-1.so
pyjrk/drivers/x64/libpololu-jrk2-1.dll
pyjrk/drivers/x64/libusbp-1.dll
pyjrk/pyjrk.py
pyjrk/pyjrk_base.py
pyjrk/pyjrk_properties.py
pyjrk/pyjrk_protocol.py
pyjrk/pyjrk_structures.py
pyjrk-0.0.2.dist-info/METADATA
pyjrk-0.0.2.dist-info/WHEEL
pyjrk-0.0.2.dist-info/licenses/LICENSE
pyjrk-0.0.2.dist-info/RECORD
