Metadata-Version: 2.4
Name: pyjrk
Version: 0.0.2
Summary: Python API of pololu jrk-g2 C library
License: Apache-2.0
License-File: LICENSE
Author: Jose Luis Morales
Author-email: jlmoraleshellin@gmail.com
Requires-Python: >=3.12,<4.0
Classifier: License :: OSI Approved :: Apache Software License
Classifier: Programming Language :: Python :: 3
Classifier: Programming Language :: Python :: 3.12
Classifier: Programming Language :: Python :: 3.13
Classifier: Programming Language :: Python :: 3.14
Requires-Dist: pyyaml (>=6.0.2,<7.0.0)
